faina_semenovna/__init__.py
faina_semenovna/faina.py
faina_semenovna/blanks/__init__.py
faina_semenovna/blanks/smz_v0_28.py
faina_semenovna/blanks/smz_v0_28_schema.py
faina_semenovna-0.1a1.dist-info/LICENSE
faina_semenovna-0.1a1.dist-info/METADATA
faina_semenovna-0.1a1.dist-info/WHEEL
faina_semenovna-0.1a1.dist-info/top_level.txt
faina_semenovna-0.1a1.dist-info/RECORD
