Metadata-Version: 2.1
Name: faina-semenovna
Version: 0.1a1
Summary: Simplifies work with XML-API for self-employed partners in Russia
Home-page: https://gitlab.com/whiteapfel/FainaSemenovna
Author: WhiteApfel
Author-email: white@pfel.ru
License: MPL 2.0
Project-URL: Дока по API от ФНС, https://npd.nalog.ru/html/sites/www.npd.nalog.ru/pinfexch_0307.docx
Project-URL: Донатик, https://pfel.cc/donate
Project-URL: Исходнички, https://gitlab.com/whiteapfel/FainaSemenovna
Project-URL: Тележка для вопросов, https://t.me/apfel
Platform: UNKNOWN
License-File: LICENSE
Requires-Dist: vitya (~=0.11.1)
Requires-Dist: xsdata (~=21.6)
Requires-Dist: typing (~=3.7.4.3)
Requires-Dist: pydantic (~=1.8.2)
Requires-Dist: lxml (~=4.6.3)
